rap_llm/BaseLLM.py
rap_llm/FormatterLLM.py
rap_llm/__init__.py
rap_llm/gpt.py
rap_llm/helpers.py
rap_llm/models.py
rap_llm-0.1.15.dist-info/METADATA
rap_llm-0.1.15.dist-info/WHEEL
rap_llm-0.1.15.dist-info/RECORD
