Metadata-Version: 2.4
Name: rap-llm
Version: 0.1.15
Summary: LLM utils created by Raptor
Author-email: raptor <aditya@clusterdev.net>
Requires-Python: >=3.13
Requires-Dist: openai>=2.8.1
Requires-Dist: pandas>=2.3.3
Requires-Dist: tqdm>=4.67.1
